featherpy/__init__.py
featherpy/_version.py
featherpy/_version.pyi
featherpy/cli.py
featherpy/core.py
featherpy/exceptions.py
featherpy/logging.py
featherpy/plotting.py
featherpy/py.typed
featherpy/weighting.py
featherpy-0.0.1.dist-info/METADATA
featherpy-0.0.1.dist-info/WHEEL
featherpy-0.0.1.dist-info/entry_points.txt
featherpy-0.0.1.dist-info/licenses/LICENSE
featherpy-0.0.1.dist-info/RECORD
