Metadata-Version: 2.3
Name: FeatherPy
Version: 0.0.1
Summary: A python package to combine radio as
Project-URL: Homepage, https://github.com/AlecThomson/FeatherPy
Project-URL: Bug Tracker, https://github.com/AlecThomson/FeatherPy/issues
Project-URL: Discussions, https://github.com/AlecThomson/FeatherPy/discussions
Project-URL: Changelog, https://github.com/AlecThomson/FeatherPy/releases
Author-email: Alec Thomson <alec.thomson@csiro.au>
Classifier: Development Status :: 1 - Planning
Classifier: Intended Audience :: Developers
Classifier: Intended Audience :: Science/Research
Classifier: License :: OSI Approved :: BSD License
Classifier: Operating System :: OS Independent
Classifier: Programming Language :: Python
Classifier: Programming Language :: Python :: 3
Classifier: Programming Language :: Python :: 3 :: Only
Classifier: Programming Language :: Python :: 3.9
Classifier: Programming Language :: Python :: 3.10
Classifier: Programming Language :: Python :: 3.11
Classifier: Programming Language :: Python :: 3.12
Classifier: Programming Language :: Python :: 3.13
Classifier: Topic :: Scientific/Engineering
Classifier: Typing :: Typed
Requires-Python: >=3.9
Requires-Dist: astropy>=6.0
Requires-Dist: matplotlib
Requires-Dist: numpy
Requires-Dist: radio-beam>=0.3.8
Requires-Dist: reproject
Requires-Dist: scipy
Provides-Extra: dev
Requires-Dist: pytest-cov>=3; extra == 'dev'
Requires-Dist: pytest>=6; extra == 'dev'
Provides-Extra: docs
Requires-Dist: furo>=2023.08.17; extra == 'docs'
Requires-Dist: myst-parser>=0.13; extra == 'docs'
Requires-Dist: sphinx-autoapi; extra == 'docs'
Requires-Dist: sphinx-autodoc-typehints; extra == 'docs'
Requires-Dist: sphinx-copybutton; extra == 'docs'
Requires-Dist: sphinx>=7.0; extra == 'docs'
Provides-Extra: test
Requires-Dist: pytest-cov>=3; extra == 'test'
Requires-Dist: pytest>=6; extra == 'test'
